Workbook

Sheet Calculator
B1: PERSONAL LOAN EMI CALCULATOR
B3: For internal assessment purpose only
B5: Input Details (Editable Fields Only) | K5: Loan Outcome
B6: Borrower Category | F6: SALARIED WITH OTHER | H6: START FROM HERE | K6: Sanctioned Loan Amount
B7: Gross Monthly Income | C7: Salary Deductions | D7: Existing EMI Obligations | E7: Requested Loan Tenure (Months) | F7: Rate of Interest (% p.a.) | G7: Maximum Permissible EMI | H7: Loan Eligibility Based on Net Income | I7: Eligible Loan Amount Based on Max Permissible EMI | K7: =MIN(Calculator!H8,Calculator!I8) -> 1000000 | R7: =B8-C8-D8 -> 77160
B8: 96000 | C8: 6520 | D8: 12320 | E8: 60 | F8: 0.116 | G8: =IF(B8<=25000,((B8*50%)-C8-D8),IF(B8<=40000,((B8*60%)-C8-D8),IF(B8<=75000,((B8*65%)-C8-D8),IF(B8>75000,((B8*70%)-C8-D8),"")))) -> 48360 | H8: =IF(F6='Ref Cell'!A3,,IF(Calculator!F6='Ref Cell'!A4,IF(Calculator!B8*30>3000000,3000000,Calculator!B8*30),IF(Calculator!F6='Ref Cell'!A5,IF(Calculator!B8*15>1000000,1000000,Calculator!B8*15),IF(Calculator!F6='Ref Cell'!A6,IF(Calculator!B8*18>300000,300000,Calculator!B8*18),IF(Calculator!F6='Ref Cell'!A7,IF(Calculator!B8*12>500000,500000,Calculator!B8*12),0))))) -> 1000000 | I8: =IF(F6='Ref Cell'!A3,,IF(Calculator!F6='Ref Cell'!A4,IF(F24>3000000,3000000,F24),IF(Calculator!F6='Ref Cell'!A5,IF(F24>1000000,1000000,F24),IF(Calculator!F6='Ref Cell'!A6,IF(F24>300000,300000,F24),IF(Calculator!F6='Ref Cell'!A7,IF(F24>500000,500000,F24),0))))) -> 1000000 | K8: Monthly EMI | L8: =ABS(PMT(F8/12,E8,K7)) -> 22042.843
K9: Loan Tenure (Months) | L9: =IF(F6='Ref Cell'!A3,,IF(Calculator!F6='Ref Cell'!A4,84,IF(Calculator!F6='Ref Cell'!A5,84,IF(Calculator!F6='Ref Cell'!A6,84,60)))) -> 84
B10: Document Checklist
B11: =IF(F6='Ref Cell'!A3," ",'Ref Cell'!B10) -> APPLICATION | G11: Fees (Non-refundable) | I11: Gross Income Calculation (Non-Salaried Applicant)
B12: =IF(Calculator!F6='Ref Cell'!A3," ",'Ref Cell'!B14) -> KYC | G12: 1% upfront fee +GST | H12: =IF(AND(K7>1000000, F6='Ref Cell'!A4), "",(K7*1.18%) ) -> 11800
B13: =IF(F6='Ref Cell'!A3," ",'Ref Cell'!B17) -> BANK STATEMENT FOR 12 MONTHS | G13: Documentation Charge | H13: =IF(AND(F6='Ref Cell'!A4, K7>1000000), 0, IF(K7<=200000, 270*1.18, 450*1.18) ) -> 531 | I13: ITR FOR LAST ASSESMENT YEAR | K13: ITR FOR THIS ASSESMENT YEAR | L13: GROSS Monthly Income
B14: =IF(F6='Ref Cell'!A3," ",(IF(Calculator!F6='Ref Cell'!A7,'Ref Cell'!B18," "))) | G14: CIC Charge | H14: =IF(K7>0,120," ") -> 120 | L14: =(I14+K14)/24 -> 0 | N14: MONTHLY INCOME-EXPENSE CHART
B15: =IF(F6='Ref Cell'!A3," ",(IF(Calculator!F6='Ref Cell'!A4,'Ref Cell'!B12,(IF(Calculator!F6='Ref Cell'!A5,'Ref Cell'!B12,(IF(Calculator!F6='Ref Cell'!A6,'Ref Cell'!B13,(IF(Calculator!F6='Ref Cell'!A7,'Ref Cell'!B13," "))))))))) -> ITR/FORM 16 FOR 2 YEARS | G15: Total Fees | H15: =SUM(H12:H14) -> 12451
B16: =IF(F6='Ref Cell'!A3," ",(IF(Calculator!F6='Ref Cell'!A4,'Ref Cell'!B15,(IF(Calculator!F6='Ref Cell'!A5,'Ref Cell'!B15," "))))) -> JOINING LETTER
B17: =IF(F6='Ref Cell'!A3," ",(IF(F6='Ref Cell'!A4,'Ref Cell'!B16,(IF(F6='Ref Cell'!A5,'Ref Cell'!B16," "))))) -> APPOINTMENT LETTER | G17: • Only non-yellow fields are editable in Input Details tab
B18: =IF(F6='Ref Cell'!A3," ",(IF(Calculator!F6='Ref Cell'!A4,'Ref Cell'!B11,(IF(Calculator!F6='Ref Cell'!A5,'Ref Cell'!B11,(IF(Calculator!F6='Ref Cell'!A6,"IF POSSIBLE PROVIDE SALARY SLIP"," "))))))) -> SALARY SLIP FOR LAST 3 MONTHS | G18: • Select Borrower Category before entering details
B19: Made by Arijeet Koraa | G19: • Rate of Interest to be referred from CIC sheet (Best of two CIC scores)
B24: GROSS MONTHLY INCOME | C24: =B8 -> 96000 | F24: =ABS(PV(F8/12,E8,G8)) -> 2193909.4
B25: DEDUCTION IN SALARY | C25: =C8 -> 6520
B26: OTHER LOAN EMI'S | C26: =D8 -> 12320
B27: PERSONAL LOAN EMI | C27: =L8 -> 22042.843

Sheet CIC
A1: CIC Rules & Rate Tables (Floating and Fixed)
A4: BorrowerType | B4: CIBIL | C4: CRIF | D4: EXPERIAN | E4: EQUIFAX | F4: REPO | G4: SPREAD | H4: FLOATING | I4: FIXED
A5: PERSONAL LOAN - Salaried Class - Drawing salary through accounts maintained with our Branches | B5: WBGB DEFENDER | F5: 5.25 | G5: 4.25 | H5: =F5+G5 -> 9.5 | I5: =H5+1 -> 10.5
B6: 800-900 | C6: 755-900 | D6: 799-900 | E6: 834-900 | F6: 5.25 | G6: 4.35 | H6: =F6+G6 -> 9.6 | I6: =H6+1 -> 10.6
B7: 700-799 | C7: 703-754 | D7: 731-798 | E7: 783-833 | F7: 5.25 | G7: 5.35 | H7: =F7+G7 -> 10.6 | I7: =H7+1 -> 11.6
B8: 600-699 | C8: 554-702 | D8: 613-730 | E8: 602-782 | F8: 5.25 | G8: 6.35 | H8: =F8+G8 -> 11.6 | I8: =H8+1 -> 12.6
A9: PERSONAL LOAN- Salaried (Drawing Salary from Other Bank Accounts), Professional, Self-Employed Individuals, Business Persons | B9: WBGB DEFENDER | F9: 5.25 | G9: 5.25 | H9: =F9+G9 -> 10.5 | I9: =H9+1 -> 11.5
B10: 800-900 | C10: 755-900 | D10: 799-900 | E10: 834-900 | F10: 5.25 | G10: 5.35 | H10: =F10+G10 -> 10.6 | I10: =H10+1 -> 11.6
B11: 700-799 | C11: 703-754 | D11: 731-798 | E11: 783-833 | F11: 5.25 | G11: 6.35 | H11: =F11+G11 -> 11.6 | I11: =H11+1 -> 12.6
B12: 600-699 | C12: 554-702 | D12: 613-730 | E12: 602-782 | F12: 5.25 | G12: 7.35 | H12: =F12+G12 -> 12.6 | I12: =H12+1 -> 13.6

Sheet Ref Cell
A3: SELECT
A4: SALARIED WITH US
A5: SALARIED WITH OTHER
A6: SSK MSK
A7: OTHER
B9: SELECT
B10: APPLICATION
B11: SALARY SLIP FOR LAST 3 MONTHS
B12: ITR/FORM 16 FOR 2 YEARS
B13: ITR FOR 2 YEARS
B14: KYC
B15: JOINING LETTER
B16: APPOINTMENT LETTER
B17: BANK STATEMENT FOR 12 MONTHS
B18: 2 YEARS TRANSACTION WITH US
A22: =#REF!*1.18% -> #REF! | B22: =#REF!-#REF!-#REF! -> #REF!
C24: SELECT
C25: CIBIL
C26: CRIF
C27: EXPERIAN
C28: EQUIFAX
